<?xml version='1.0' encoding='UTF-8'?>
<ISRLSPANS sourcefile="msamr_dfa_091">
  <implicit role="arg1|ask.01" recoverable="True" implicit-role-type="cross-sentence-anaphoric" sentence="40" predstart="3" predend="3" pos="VERB">
    <candidate sentence="39" start="2" end="2"/>
  </implicit>
  <implicit role="arg1|typical.02" recoverable="True" implicit-role-type="cross-sentence-anaphoric" sentence="15" predstart="1" predend="1" pos="ADJ">
    <candidate sentence="14" start="2" end="2"/>
    <candidate sentence="14" start="8" end="8"/>
  </implicit>
  <implicit role="arg0|effect.03" recoverable="True" implicit-role-type="cross-sentence-cataphoric" sentence="49" predstart="6" predend="6" pos="NOUN">
    <candidate sentence="51" start="24" end="25"/>
    <candidate sentence="52" start="14" end="15"/>
  </implicit>
  <implicit role="arg2|say.01" recoverable="True" implicit-role-type="same-sentence" sentence="7" predstart="2" predend="2" pos="VERB">
    <candidate sentence="6" start="14" end="46"/>
    <candidate sentence="8" start="6" end="6"/>
    <candidate sentence="7" start="5" end="5"/>
  </implicit>
  <implicit role="arg0|talk.01" recoverable="True" implicit-role-type="same-sentence" sentence="8" predstart="8" predend="8" pos="VERB">
    <candidate sentence="6" start="14" end="46"/>
    <candidate sentence="8" start="6" end="6"/>
    <candidate sentence="7" start="5" end="5"/>
  </implicit>
  <implicit role="arg0|issue.02" recoverable="True" implicit-role-type="cross-sentence-anaphoric" sentence="31" predstart="27" predend="27" pos="NOUN">
    <candidate sentence="6" start="6" end="10"/>
    <candidate sentence="27" start="4" end="5"/>
    <candidate sentence="28" start="19" end="19"/>
    <candidate sentence="5" start="11" end="11"/>
  </implicit>
  <implicit role="arg2|wrong.04" recoverable="True" implicit-role-type="cross-sentence-anaphoric" sentence="7" predstart="11" predend="11" pos="ADJ">
    <candidate sentence="6" start="30" end="46"/>
  </implicit>
  <implicit role="arg1|advise.01" recoverable="True" implicit-role-type="cross-sentence-anaphoric" sentence="31" predstart="20" predend="20" pos="NOUN">
    <candidate sentence="11" start="15" end="15"/>
    <candidate sentence="25" start="0" end="0"/>
    <candidate sentence="26" start="0" end="0"/>
    <candidate sentence="21" start="1" end="1"/>
    <candidate sentence="9" start="0" end="0"/>
    <candidate sentence="40" start="0" end="0"/>
    <candidate sentence="16" start="0" end="0"/>
    <candidate sentence="2" start="0" end="0"/>
    <candidate sentence="1" start="0" end="0"/>
    <candidate sentence="3" start="0" end="0"/>
    <candidate sentence="39" start="0" end="0"/>
    <candidate sentence="29" start="0" end="0"/>
    <candidate sentence="23" start="0" end="0"/>
    <candidate sentence="22" start="1" end="1"/>
    <candidate sentence="24" start="0" end="0"/>
    <candidate sentence="20" start="1" end="1"/>
  </implicit>
  <implicit role="arg1|interact.01" recoverable="True" implicit-role-type="cross-sentence-anaphoric" sentence="50" predstart="23" predend="23" pos="VERB">
    <candidate sentence="27" start="8" end="9"/>
    <candidate sentence="6" start="34" end="35"/>
    <candidate sentence="28" start="1" end="1"/>
    <candidate sentence="30" start="12" end="12"/>
    <candidate sentence="29" start="29" end="30"/>
    <candidate sentence="34" start="6" end="7"/>
    <candidate sentence="6" start="10" end="10"/>
    <candidate sentence="38" start="11" end="12"/>
    <candidate sentence="27" start="11" end="12"/>
    <candidate sentence="0" start="6" end="7"/>
    <candidate sentence="5" start="9" end="9"/>
  </implicit>
  <implicit role="arg1|take.01" recoverable="True" implicit-role-type="cross-sentence-anaphoric" sentence="50" predstart="17" predend="17" pos="NOUN">
    <candidate sentence="27" start="8" end="9"/>
    <candidate sentence="6" start="34" end="35"/>
    <candidate sentence="28" start="1" end="1"/>
    <candidate sentence="30" start="12" end="12"/>
    <candidate sentence="29" start="29" end="30"/>
    <candidate sentence="34" start="6" end="7"/>
    <candidate sentence="6" start="10" end="10"/>
    <candidate sentence="38" start="11" end="12"/>
    <candidate sentence="27" start="11" end="12"/>
    <candidate sentence="0" start="6" end="7"/>
    <candidate sentence="5" start="9" end="9"/>
  </implicit>
  <implicit role="arg0|experience.01" recoverable="True" implicit-role-type="same-sentence" sentence="45" predstart="9" predend="9" pos="NOUN">
    <candidate sentence="45" start="5" end="5"/>
    <candidate sentence="46" start="0" end="0"/>
    <candidate sentence="43" start="0" end="0"/>
    <candidate sentence="44" start="0" end="0"/>
    <candidate sentence="47" start="0" end="0"/>
  </implicit>
  <implicit role="arg2|take.01" recoverable="False" implicit-role-type="missing" sentence="28" predstart="0" predend="0" pos="VERB"/>
  <implicit role="arg3|take.01" recoverable="False" implicit-role-type="missing" sentence="28" predstart="0" predend="0" pos="VERB"/>
  <implicit role="arg3|take.01" recoverable="False" implicit-role-type="missing" sentence="27" predstart="7" predend="7" pos="VERB"/>
  <implicit role="arg0|dry.08" recoverable="False" implicit-role-type="missing" sentence="27" predstart="4" predend="4" pos="ADJ"/>
  <implicit role="arg2|take.01" recoverable="False" implicit-role-type="missing" sentence="27" predstart="7" predend="7" pos="VERB"/>
  <implicit role="arg2|stop.01" recoverable="False" implicit-role-type="missing" sentence="27" predstart="10" predend="10" pos="VERB"/>
  <implicit role="arg2|dry.08" recoverable="False" implicit-role-type="missing" sentence="27" predstart="4" predend="4" pos="ADJ"/>
  <implicit role="arg0|dry.08" recoverable="False" implicit-role-type="missing" sentence="47" predstart="4" predend="4" pos="ADJ"/>
  <implicit role="arg2|dry.08" recoverable="False" implicit-role-type="missing" sentence="47" predstart="4" predend="4" pos="ADJ"/>
  <implicit role="arg2|agree.01" recoverable="False" implicit-role-type="missing" sentence="47" predstart="8" predend="8" pos="VERB"/>
  <implicit role="arg0|intend.01" recoverable="False" implicit-role-type="missing" sentence="47" predstart="13" predend="13" pos="ADJ"/>
  <implicit role="arg2|control.01" recoverable="False" implicit-role-type="missing" sentence="59" predstart="11" predend="11" pos="VERB"/>
  <implicit role="arg2|learn.01" recoverable="False" implicit-role-type="missing" sentence="59" predstart="8" predend="8" pos="VERB"/>
  <implicit role="arg2|dry.02" recoverable="False" implicit-role-type="missing" sentence="62" predstart="4" predend="4" pos="ADJ"/>
  <implicit role="arg2|loose.04" recoverable="False" implicit-role-type="missing" sentence="61" predstart="33" predend="33" pos="ADJ"/>
  <implicit role="arg0|loose.04" recoverable="False" implicit-role-type="missing" sentence="61" predstart="33" predend="33" pos="ADJ"/>
  <implicit role="arg3|lose.02" recoverable="False" implicit-role-type="missing" sentence="61" predstart="35" predend="35" pos="VERB"/>
  <implicit role="arg2|figure_out.05" recoverable="False" implicit-role-type="missing" sentence="19" predstart="12" predend="12" pos="VERB"/>
  <implicit role="arg2|dry.02" recoverable="False" implicit-role-type="missing" sentence="19" predstart="5" predend="5" pos="VERB"/>
  <implicit role="arg2|die.01" recoverable="False" implicit-role-type="missing" sentence="19" predstart="8" predend="8" pos="VERB"/>
  <implicit role="arg0|dry.02" recoverable="False" implicit-role-type="missing" sentence="19" predstart="5" predend="5" pos="VERB"/>
  <implicit role="arg2|keep.02" recoverable="False" implicit-role-type="missing" sentence="22" predstart="24" predend="24" pos="VERB"/>
  <implicit role="arg1|pile_up.02" recoverable="False" implicit-role-type="missing" sentence="22" predstart="9" predend="9" pos="VERB"/>
  <implicit role="arg0|dry.02" recoverable="False" implicit-role-type="missing" sentence="22" predstart="5" predend="5" pos="ADJ"/>
  <implicit role="arg0|poke.01" recoverable="False" implicit-role-type="missing" sentence="22" predstart="51" predend="51" pos="VERB"/>
  <implicit role="arg0|pile_up.02" recoverable="False" implicit-role-type="missing" sentence="22" predstart="9" predend="9" pos="VERB"/>
  <implicit role="arg2|dry.02" recoverable="False" implicit-role-type="missing" sentence="22" predstart="5" predend="5" pos="ADJ"/>
  <implicit role="arg0|crack.02" recoverable="False" implicit-role-type="missing" sentence="22" predstart="40" predend="40" pos="VERB"/>
  <implicit role="arg2|feel.01" recoverable="False" implicit-role-type="missing" sentence="22" predstart="44" predend="44" pos="VERB"/>
  <implicit role="arg2|keep.02" recoverable="False" implicit-role-type="missing" sentence="22" predstart="39" predend="39" pos="VERB"/>
  <implicit role="arg1|crack.02" recoverable="False" implicit-role-type="missing" sentence="22" predstart="40" predend="40" pos="VERB"/>
  <implicit role="arg2|sand.01" recoverable="False" implicit-role-type="missing" sentence="22" predstart="18" predend="18" pos="VERB"/>
  <implicit role="arg2|crack.02" recoverable="False" implicit-role-type="missing" sentence="22" predstart="40" predend="40" pos="VERB"/>
  <implicit role="arg0|dry.08" recoverable="False" implicit-role-type="missing" sentence="21" predstart="11" predend="11" pos="ADJ"/>
  <implicit role="arg2|dry.08" recoverable="False" implicit-role-type="missing" sentence="21" predstart="11" predend="11" pos="ADJ"/>
  <implicit role="arg3|lose.02" recoverable="False" implicit-role-type="missing" sentence="21" predstart="3" predend="3" pos="VERB"/>
  <implicit role="arg1|err.01" recoverable="False" implicit-role-type="missing" sentence="24" predstart="10" predend="10" pos="NOUN"/>
  <implicit role="arg4|recommend.01" recoverable="False" implicit-role-type="missing" sentence="24" predstart="1" predend="1" pos="VERB"/>
  <implicit role="arg0|recommend.01" recoverable="False" implicit-role-type="missing" sentence="24" predstart="1" predend="1" pos="VERB"/>
  <implicit role="arg0|damage.01" recoverable="False" implicit-role-type="missing" sentence="23" predstart="16" predend="16" pos="VERB"/>
  <implicit role="arg2|stop.01" recoverable="False" implicit-role-type="missing" sentence="23" predstart="1" predend="1" pos="VERB"/>
  <implicit role="arg3|go.01" recoverable="False" implicit-role-type="missing" sentence="23" predstart="9" predend="9" pos="VERB"/>
  <implicit role="arg2|damage.01" recoverable="False" implicit-role-type="missing" sentence="23" predstart="16" predend="16" pos="VERB"/>
  <implicit role="arg4|go.01" recoverable="False" implicit-role-type="missing" sentence="23" predstart="9" predend="9" pos="VERB"/>
  <implicit role="arg2|go.01" recoverable="False" implicit-role-type="missing" sentence="23" predstart="9" predend="9" pos="VERB"/>
  <implicit role="arg2|dry.08" recoverable="False" implicit-role-type="missing" sentence="25" predstart="11" predend="11" pos="ADJ"/>
  <implicit role="arg2|dent.01" recoverable="False" implicit-role-type="missing" sentence="25" predstart="20" predend="20" pos="NOUN"/>
  <implicit role="arg0|dry.08" recoverable="False" implicit-role-type="missing" sentence="25" predstart="11" predend="11" pos="ADJ"/>
  <implicit role="arg2|high.02" recoverable="False" implicit-role-type="missing" sentence="48" predstart="4" predend="4" pos="ADJ"/>
  <implicit role="arg2|take.01" recoverable="False" implicit-role-type="missing" sentence="48" predstart="3" predend="3" pos="VERB"/>
  <implicit role="arg3|take.01" recoverable="False" implicit-role-type="missing" sentence="48" predstart="3" predend="3" pos="VERB"/>
  <implicit role="arg2|consider.02" recoverable="False" implicit-role-type="missing" sentence="38" predstart="0" predend="0" pos="VERB"/>
  <implicit role="arg3|firm.01" recoverable="False" implicit-role-type="missing" sentence="60" predstart="13" predend="13" pos="VERB"/>
  <implicit role="arg3|normal.02" recoverable="False" implicit-role-type="missing" sentence="60" predstart="1" predend="1" pos="ADJ"/>
  <implicit role="arg3|get.01" recoverable="False" implicit-role-type="missing" sentence="60" predstart="4" predend="4" pos="VERB"/>
  <implicit role="arg2|firm.01" recoverable="False" implicit-role-type="missing" sentence="60" predstart="13" predend="13" pos="VERB"/>
  <implicit role="arg0|blow.14" recoverable="False" implicit-role-type="missing" sentence="60" predstart="6" predend="6" pos="NOUN"/>
  <implicit role="arg2|normal.02" recoverable="False" implicit-role-type="missing" sentence="60" predstart="1" predend="1" pos="ADJ"/>
  <implicit role="arg2|blow.14" recoverable="False" implicit-role-type="missing" sentence="60" predstart="6" predend="6" pos="NOUN"/>
  <implicit role="arg1|comment.01" recoverable="False" implicit-role-type="missing" sentence="42" predstart="1" predend="1" pos="VERB"/>
  <implicit role="arg2|comment.01" recoverable="False" implicit-role-type="missing" sentence="42" predstart="1" predend="1" pos="VERB"/>
  <implicit role="arg1|advise.01" recoverable="False" implicit-role-type="missing" sentence="42" predstart="6" predend="6" pos="NOUN"/>
  <implicit role="arg2|destroy.01" recoverable="False" implicit-role-type="missing" sentence="41" predstart="11" predend="11" pos="VERB"/>
  <implicit role="arg2|consider.02" recoverable="False" implicit-role-type="missing" sentence="41" predstart="0" predend="0" pos="VERB"/>
  <implicit role="arg0|destroy.01" recoverable="False" implicit-role-type="missing" sentence="41" predstart="11" predend="11" pos="VERB"/>
  <implicit role="arg2|destroy.01" recoverable="False" implicit-role-type="missing" sentence="41" predstart="5" predend="5" pos="VERB"/>
  <implicit role="arg0|destroy.01" recoverable="False" implicit-role-type="missing" sentence="41" predstart="5" predend="5" pos="VERB"/>
  <implicit role="arg0|obligate.01" recoverable="False" implicit-role-type="missing" sentence="40" predstart="1" predend="1" pos="VERB"/>
  <implicit role="arg3|recall.02" recoverable="False" implicit-role-type="missing" sentence="39" predstart="13" predend="13" pos="VERB"/>
  <implicit role="arg0|recall.02" recoverable="False" implicit-role-type="missing" sentence="39" predstart="13" predend="13" pos="VERB"/>
  <implicit role="arg2|say.01" recoverable="False" implicit-role-type="missing" sentence="39" predstart="5" predend="5" pos="VERB"/>
  <implicit role="arg2|know.01" recoverable="False" implicit-role-type="missing" sentence="46" predstart="6" predend="6" pos="VERB"/>
  <implicit role="arg2|know.01" recoverable="False" implicit-role-type="missing" sentence="45" predstart="6" predend="6" pos="VERB"/>
  <implicit role="arg0|switch.01" recoverable="False" implicit-role-type="missing" sentence="44" predstart="21" predend="21" pos="VERB"/>
  <implicit role="arg3|switch.01" recoverable="False" implicit-role-type="missing" sentence="44" predstart="21" predend="21" pos="VERB"/>
  <implicit role="arg3|take.01" recoverable="False" implicit-role-type="missing" sentence="44" predstart="4" predend="4" pos="VERB"/>
  <implicit role="arg2|take.01" recoverable="False" implicit-role-type="missing" sentence="44" predstart="4" predend="4" pos="VERB"/>
  <implicit role="arg2|specific.02" recoverable="False" implicit-role-type="missing" sentence="44" predstart="5" predend="5" pos="ADJ"/>
  <implicit role="arg2|start.01" recoverable="False" implicit-role-type="missing" sentence="43" predstart="2" predend="2" pos="VERB"/>
  <implicit role="arg2|comment.01" recoverable="False" implicit-role-type="missing" sentence="37" predstart="4" predend="4" pos="NOUN"/>
  <implicit role="arg1|sad.02" recoverable="False" implicit-role-type="missing" sentence="37" predstart="3" predend="3" pos="ADJ"/>
  <implicit role="arg2|learn.01" recoverable="False" implicit-role-type="missing" sentence="37" predstart="10" predend="10" pos="VERB"/>
  <implicit role="arg0|comment.01" recoverable="False" implicit-role-type="missing" sentence="37" predstart="4" predend="4" pos="NOUN"/>
  <implicit role="arg2|sad.02" recoverable="False" implicit-role-type="missing" sentence="37" predstart="3" predend="3" pos="ADJ"/>
  <implicit role="arg0|obligate.01" recoverable="False" implicit-role-type="missing" sentence="37" predstart="7" predend="7" pos="VERB"/>
  <implicit role="arg2|trouble.01" recoverable="False" implicit-role-type="missing" sentence="31" predstart="16" predend="16" pos="VERB"/>
  <implicit role="arg2|tell.02" recoverable="False" implicit-role-type="missing" sentence="31" predstart="30" predend="30" pos="VERB"/>
  <implicit role="arg0|tell.02" recoverable="False" implicit-role-type="missing" sentence="31" predstart="30" predend="30" pos="VERB"/>
  <implicit role="arg2|upset.01" recoverable="False" implicit-role-type="missing" sentence="31" predstart="9" predend="9" pos="ADJ"/>
  <implicit role="arg0|bad.07" recoverable="False" implicit-role-type="missing" sentence="63" predstart="7" predend="7" pos="ADJ"/>
  <implicit role="arg3|read.01" recoverable="False" implicit-role-type="missing" sentence="63" predstart="12" predend="12" pos="VERB"/>
  <implicit role="arg0|see.01" recoverable="False" implicit-role-type="missing" sentence="32" predstart="2" predend="2" pos="NOUN"/>
  <implicit role="arg0|degenerate.01" recoverable="False" implicit-role-type="missing" sentence="32" predstart="7" predend="7" pos="NOUN"/>
  <implicit role="arg3|lose.02" recoverable="False" implicit-role-type="missing" sentence="32" predstart="3" predend="3" pos="NOUN"/>
  <implicit role="arg4|degenerate.01" recoverable="False" implicit-role-type="missing" sentence="32" predstart="7" predend="7" pos="NOUN"/>
  <implicit role="arg2|general.02" recoverable="False" implicit-role-type="missing" sentence="32" predstart="19" predend="19" pos="ADJ"/>
  <implicit role="arg0|lose.02" recoverable="False" implicit-role-type="missing" sentence="32" predstart="10" predend="10" pos="NOUN"/>
  <implicit role="arg2|degenerate.01" recoverable="False" implicit-role-type="missing" sentence="32" predstart="7" predend="7" pos="NOUN"/>
  <implicit role="arg0|lose.02" recoverable="False" implicit-role-type="missing" sentence="32" predstart="3" predend="3" pos="NOUN"/>
  <implicit role="arg2|constipate.01" recoverable="False" implicit-role-type="missing" sentence="32" predstart="14" predend="14" pos="NOUN"/>
  <implicit role="arg0|use.01" recoverable="False" implicit-role-type="missing" sentence="32" predstart="20" predend="20" pos="NOUN"/>
  <implicit role="arg1|see.01" recoverable="False" implicit-role-type="missing" sentence="32" predstart="2" predend="2" pos="NOUN"/>
  <implicit role="arg0|constipate.01" recoverable="False" implicit-role-type="missing" sentence="32" predstart="14" predend="14" pos="NOUN"/>
  <implicit role="arg3|degenerate.01" recoverable="False" implicit-role-type="missing" sentence="32" predstart="7" predend="7" pos="NOUN"/>
  <implicit role="arg1|constipate.01" recoverable="False" implicit-role-type="missing" sentence="32" predstart="14" predend="14" pos="NOUN"/>
  <implicit role="arg2|use.01" recoverable="False" implicit-role-type="missing" sentence="32" predstart="20" predend="20" pos="NOUN"/>
  <implicit role="arg3|lose.02" recoverable="False" implicit-role-type="missing" sentence="32" predstart="10" predend="10" pos="NOUN"/>
  <implicit role="arg0|dry.02" recoverable="False" implicit-role-type="missing" sentence="9" predstart="19" predend="19" pos="ADJ"/>
  <implicit role="arg2|dry.02" recoverable="False" implicit-role-type="missing" sentence="9" predstart="19" predend="19" pos="ADJ"/>
  <implicit role="arg2|take.01" recoverable="False" implicit-role-type="missing" sentence="10" predstart="13" predend="13" pos="NOUN"/>
  <implicit role="arg2|dry.08" recoverable="False" implicit-role-type="missing" sentence="10" predstart="19" predend="19" pos="ADJ"/>
  <implicit role="arg3|take.01" recoverable="False" implicit-role-type="missing" sentence="10" predstart="13" predend="13" pos="NOUN"/>
  <implicit role="arg0|take.01" recoverable="False" implicit-role-type="missing" sentence="10" predstart="13" predend="13" pos="NOUN"/>
  <implicit role="arg1|leave.11" recoverable="False" implicit-role-type="missing" sentence="10" predstart="21" predend="21" pos="VERB"/>
  <implicit role="arg0|dry.08" recoverable="False" implicit-role-type="missing" sentence="10" predstart="19" predend="19" pos="ADJ"/>
  <implicit role="arg2|leave.11" recoverable="False" implicit-role-type="missing" sentence="10" predstart="21" predend="21" pos="VERB"/>
  <implicit role="arg2|take.01" recoverable="False" implicit-role-type="missing" sentence="11" predstart="5" predend="5" pos="VERB"/>
  <implicit role="arg3|come.01" recoverable="False" implicit-role-type="missing" sentence="11" predstart="12" predend="12" pos="VERB"/>
  <implicit role="arg3|reduce.01" recoverable="False" implicit-role-type="missing" sentence="11" predstart="28" predend="28" pos="VERB"/>
  <implicit role="arg2|terrible.01" recoverable="False" implicit-role-type="missing" sentence="11" predstart="22" predend="22" pos="ADJ"/>
  <implicit role="arg2|come.01" recoverable="False" implicit-role-type="missing" sentence="11" predstart="12" predend="12" pos="VERB"/>
  <implicit role="arg0|dry.02" recoverable="False" implicit-role-type="missing" sentence="11" predstart="42" predend="42" pos="ADJ"/>
  <implicit role="arg2|dry.02" recoverable="False" implicit-role-type="missing" sentence="11" predstart="23" predend="23" pos="ADJ"/>
  <implicit role="arg2|reduce.01" recoverable="False" implicit-role-type="missing" sentence="11" predstart="28" predend="28" pos="VERB"/>
  <implicit role="arg3|take.01" recoverable="False" implicit-role-type="missing" sentence="11" predstart="5" predend="5" pos="VERB"/>
  <implicit role="arg2|dry.02" recoverable="False" implicit-role-type="missing" sentence="11" predstart="42" predend="42" pos="ADJ"/>
  <implicit role="arg0|dry.02" recoverable="False" implicit-role-type="missing" sentence="11" predstart="23" predend="23" pos="ADJ"/>
  <implicit role="arg0|word.01" recoverable="False" implicit-role-type="missing" sentence="12" predstart="2" predend="2" pos="NOUN"/>
  <implicit role="arg0|start.01" recoverable="False" implicit-role-type="missing" sentence="12" predstart="17" predend="17" pos="VERB"/>
  <implicit role="arg0|follow.02" recoverable="False" implicit-role-type="missing" sentence="12" predstart="5" predend="5" pos="VERB"/>
  <implicit role="arg2|start.01" recoverable="False" implicit-role-type="missing" sentence="12" predstart="17" predend="17" pos="VERB"/>
  <implicit role="arg2|kill.01" recoverable="False" implicit-role-type="missing" sentence="12" predstart="19" predend="19" pos="VERB"/>
  <implicit role="arg0|try.01" recoverable="False" implicit-role-type="missing" sentence="14" predstart="8" predend="8" pos="VERB"/>
  <implicit role="arg3|take.01" recoverable="False" implicit-role-type="missing" sentence="14" predstart="13" predend="13" pos="VERB"/>
  <implicit role="arg2|take.01" recoverable="False" implicit-role-type="missing" sentence="14" predstart="13" predend="13" pos="VERB"/>
  <implicit role="arg2|dismiss.01" recoverable="False" implicit-role-type="missing" sentence="14" predstart="2" predend="2" pos="VERB"/>
  <implicit role="arg0|get.04" recoverable="False" implicit-role-type="missing" sentence="14" predstart="10" predend="10" pos="VERB"/>
  <implicit role="arg2|claim.01" recoverable="False" implicit-role-type="missing" sentence="14" predstart="6" predend="6" pos="VERB"/>
  <implicit role="arg1|correct.01" recoverable="False" implicit-role-type="missing" sentence="14" predstart="14" predend="14" pos="ADJ"/>
  <implicit role="arg4|go.01" recoverable="False" implicit-role-type="missing" sentence="16" predstart="20" predend="20" pos="VERB"/>
  <implicit role="arg2|dry.02" recoverable="False" implicit-role-type="missing" sentence="16" predstart="9" predend="9" pos="ADJ"/>
  <implicit role="arg2|dry.02" recoverable="False" implicit-role-type="missing" sentence="16" predstart="2" predend="2" pos="ADJ"/>
  <implicit role="arg2|stop.01" recoverable="False" implicit-role-type="missing" sentence="16" predstart="15" predend="15" pos="VERB"/>
  <implicit role="arg0|dry.02" recoverable="False" implicit-role-type="missing" sentence="16" predstart="9" predend="9" pos="ADJ"/>
  <implicit role="arg2|go.01" recoverable="False" implicit-role-type="missing" sentence="16" predstart="20" predend="20" pos="VERB"/>
  <implicit role="arg3|go.01" recoverable="False" implicit-role-type="missing" sentence="16" predstart="20" predend="20" pos="VERB"/>
  <implicit role="arg0|dry.02" recoverable="False" implicit-role-type="missing" sentence="16" predstart="2" predend="2" pos="ADJ"/>
  <implicit role="arg2|same.01" recoverable="False" implicit-role-type="missing" sentence="17" predstart="12" predend="12" pos="ADJ"/>
  <implicit role="arg2|conclude.01" recoverable="False" implicit-role-type="missing" sentence="17" predstart="13" predend="13" pos="NOUN"/>
  <implicit role="arg3|conclude.01" recoverable="False" implicit-role-type="missing" sentence="17" predstart="13" predend="13" pos="NOUN"/>
  <implicit role="arg0|relate.01" recoverable="False" implicit-role-type="missing" sentence="17" predstart="5" predend="5" pos="ADJ"/>
  <implicit role="arg2|relate.01" recoverable="False" implicit-role-type="missing" sentence="17" predstart="5" predend="5" pos="ADJ"/>
  <implicit role="arg2|trust.01" recoverable="False" implicit-role-type="missing" sentence="18" predstart="5" predend="5" pos="VERB"/>
  <implicit role="arg0|credential.01" recoverable="False" implicit-role-type="missing" sentence="18" predstart="20" predend="20" pos="NOUN"/>
  <implicit role="arg2|general.02" recoverable="False" implicit-role-type="missing" sentence="18" predstart="7" predend="7" pos="ADJ"/>
  <implicit role="arg2|advise.01" recoverable="False" implicit-role-type="missing" sentence="18" predstart="23" predend="23" pos="NOUN"/>
  <implicit role="arg1|advise.01" recoverable="False" implicit-role-type="missing" sentence="18" predstart="23" predend="23" pos="NOUN"/>
  <implicit role="arg3|get.01" recoverable="False" implicit-role-type="missing" sentence="29" predstart="15" predend="15" pos="VERB"/>
  <implicit role="arg2|require.01" recoverable="False" implicit-role-type="missing" sentence="29" predstart="28" predend="28" pos="VERB"/>
  <implicit role="arg0|require.01" recoverable="False" implicit-role-type="missing" sentence="30" predstart="9" predend="9" pos="VERB"/>
  <implicit role="arg2|require.01" recoverable="False" implicit-role-type="missing" sentence="30" predstart="9" predend="9" pos="VERB"/>
  <implicit role="arg0|prescribe.02" recoverable="False" implicit-role-type="missing" sentence="35" predstart="17" predend="17" pos="ADJ"/>
  <implicit role="arg2|prescribe.02" recoverable="False" implicit-role-type="missing" sentence="35" predstart="17" predend="17" pos="ADJ"/>
  <implicit role="arg2|regular.02" recoverable="False" implicit-role-type="missing" sentence="35" predstart="7" predend="7" pos="ADJ"/>
  <implicit role="arg2|recommend.01" recoverable="False" implicit-role-type="missing" sentence="35" predstart="1" predend="1" pos="VERB"/>
  <implicit role="arg0|recommend.01" recoverable="False" implicit-role-type="missing" sentence="35" predstart="1" predend="1" pos="VERB"/>
  <implicit role="arg3|regular.02" recoverable="False" implicit-role-type="missing" sentence="35" predstart="7" predend="7" pos="ADJ"/>
  <implicit role="arg0|explain.01" recoverable="False" implicit-role-type="missing" sentence="35" predstart="3" predend="3" pos="VERB"/>
  <implicit role="arg2|use.01" recoverable="False" implicit-role-type="missing" sentence="35" predstart="8" predend="8" pos="NOUN"/>
  <implicit role="arg0|follow.02" recoverable="False" implicit-role-type="missing" sentence="35" predstart="15" predend="15" pos="VERB"/>
  <implicit role="arg4|recommend.01" recoverable="False" implicit-role-type="missing" sentence="35" predstart="1" predend="1" pos="VERB"/>
  <implicit role="arg0|use.01" recoverable="False" implicit-role-type="missing" sentence="35" predstart="8" predend="8" pos="NOUN"/>
  <implicit role="arg3|take.01" recoverable="False" implicit-role-type="missing" sentence="36" predstart="20" predend="20" pos="VERB"/>
  <implicit role="arg2|dry.08" recoverable="False" implicit-role-type="missing" sentence="36" predstart="24" predend="24" pos="ADJ"/>
  <implicit role="arg2|stop.01" recoverable="False" implicit-role-type="missing" sentence="36" predstart="26" predend="26" pos="VERB"/>
  <implicit role="arg0|stop.01" recoverable="False" implicit-role-type="missing" sentence="36" predstart="26" predend="26" pos="VERB"/>
  <implicit role="arg2|advise.01" recoverable="False" implicit-role-type="missing" sentence="36" predstart="41" predend="41" pos="VERB"/>
  <implicit role="arg0|take.01" recoverable="False" implicit-role-type="missing" sentence="36" predstart="0" predend="0" pos="VERB"/>
  <implicit role="arg3|take.01" recoverable="False" implicit-role-type="missing" sentence="36" predstart="0" predend="0" pos="VERB"/>
  <implicit role="arg0|dry.08" recoverable="False" implicit-role-type="missing" sentence="36" predstart="24" predend="24" pos="ADJ"/>
  <implicit role="arg2|take.01" recoverable="False" implicit-role-type="missing" sentence="36" predstart="20" predend="20" pos="VERB"/>
  <implicit role="arg4|recommend.01" recoverable="False" implicit-role-type="missing" sentence="33" predstart="9" predend="9" pos="VERB"/>
  <implicit role="arg0|recommend.01" recoverable="False" implicit-role-type="missing" sentence="33" predstart="9" predend="9" pos="VERB"/>
  <implicit role="arg0|recommend.01" recoverable="False" implicit-role-type="missing" sentence="34" predstart="2" predend="2" pos="VERB"/>
  <implicit role="arg2|recommend.01" recoverable="False" implicit-role-type="missing" sentence="34" predstart="2" predend="2" pos="VERB"/>
  <implicit role="arg4|recommend.01" recoverable="False" implicit-role-type="missing" sentence="34" predstart="2" predend="2" pos="VERB"/>
  <implicit role="arg0|give.01" recoverable="False" implicit-role-type="missing" sentence="34" predstart="5" predend="5" pos="VERB"/>
  <implicit role="arg3|take.01" recoverable="False" implicit-role-type="missing" sentence="57" predstart="27" predend="27" pos="VERB"/>
  <implicit role="arg0|increase.01" recoverable="False" implicit-role-type="missing" sentence="57" predstart="50" predend="50" pos="VERB"/>
  <implicit role="arg3|increase.01" recoverable="False" implicit-role-type="missing" sentence="57" predstart="50" predend="50" pos="VERB"/>
  <implicit role="arg2|round.05" recoverable="False" implicit-role-type="missing" sentence="57" predstart="29" predend="29" pos="NOUN"/>
  <implicit role="arg0|produce.01" recoverable="False" implicit-role-type="missing" sentence="57" predstart="52" predend="52" pos="NOUN"/>
  <implicit role="arg2|increase.01" recoverable="False" implicit-role-type="missing" sentence="57" predstart="50" predend="50" pos="VERB"/>
  <implicit role="arg2|take.01" recoverable="False" implicit-role-type="missing" sentence="57" predstart="27" predend="27" pos="VERB"/>
  <implicit role="arg4|increase.01" recoverable="False" implicit-role-type="missing" sentence="57" predstart="50" predend="50" pos="VERB"/>
  <implicit role="arg2|start.01" recoverable="False" implicit-role-type="missing" sentence="57" predstart="6" predend="6" pos="VERB"/>
  <implicit role="arg2|produce.01" recoverable="False" implicit-role-type="missing" sentence="57" predstart="52" predend="52" pos="NOUN"/>
  <implicit role="arg3|pull.01" recoverable="False" implicit-role-type="missing" sentence="57" predstart="7" predend="7" pos="VERB"/>
  <implicit role="arg2|work.09" recoverable="False" implicit-role-type="missing" sentence="53" predstart="12" predend="12" pos="VERB"/>
  <implicit role="arg1|compare.01" recoverable="False" implicit-role-type="missing" sentence="53" predstart="6" predend="6" pos="NOUN"/>
  <implicit role="arg0|work.09" recoverable="False" implicit-role-type="missing" sentence="53" predstart="12" predend="12" pos="VERB"/>
  <implicit role="arg2|compare.01" recoverable="False" implicit-role-type="missing" sentence="53" predstart="6" predend="6" pos="NOUN"/>
  <implicit role="arg0|obligate.01" recoverable="False" implicit-role-type="missing" sentence="53" predstart="1" predend="1" pos="VERB"/>
  <implicit role="arg0|concentrate.02" recoverable="False" implicit-role-type="missing" sentence="54" predstart="17" predend="17" pos="ADJ"/>
  <implicit role="arg2|high.02" recoverable="False" implicit-role-type="missing" sentence="54" predstart="4" predend="4" pos="ADJ"/>
  <implicit role="arg0|dry.08" recoverable="False" implicit-role-type="missing" sentence="55" predstart="3" predend="3" pos="ADJ"/>
  <implicit role="arg2|high.02" recoverable="False" implicit-role-type="missing" sentence="55" predstart="7" predend="7" pos="ADJ"/>
  <implicit role="arg2|dry.08" recoverable="False" implicit-role-type="missing" sentence="55" predstart="3" predend="3" pos="ADJ"/>
  <implicit role="arg2|control.01" recoverable="False" implicit-role-type="missing" sentence="56" predstart="7" predend="7" pos="VERB"/>
  <implicit role="arg3|know.02" recoverable="False" implicit-role-type="missing" sentence="49" predstart="3" predend="3" pos="VERB"/>
  <implicit role="arg2|take.01" recoverable="False" implicit-role-type="missing" sentence="51" predstart="12" predend="12" pos="VERB"/>
  <implicit role="arg0|take.01" recoverable="False" implicit-role-type="missing" sentence="51" predstart="12" predend="12" pos="VERB"/>
  <implicit role="arg2|take.01" recoverable="False" implicit-role-type="missing" sentence="51" predstart="5" predend="5" pos="VERB"/>
  <implicit role="arg3|take.01" recoverable="False" implicit-role-type="missing" sentence="51" predstart="5" predend="5" pos="VERB"/>
  <implicit role="arg3|take.01" recoverable="False" implicit-role-type="missing" sentence="51" predstart="12" predend="12" pos="VERB"/>
  <implicit role="arg1|exemplify.01" recoverable="False" implicit-role-type="missing" sentence="51" predstart="1" predend="1" pos="NOUN"/>
  <implicit role="arg3|take.01" recoverable="False" implicit-role-type="missing" sentence="51" predstart="23" predend="23" pos="VERB"/>
  <implicit role="arg1|advise.01" recoverable="False" implicit-role-type="missing" sentence="51" predstart="9" predend="9" pos="VERB"/>
  <implicit role="arg2|take.01" recoverable="False" implicit-role-type="missing" sentence="51" predstart="23" predend="23" pos="VERB"/>
  <implicit role="arg0|take.01" recoverable="False" implicit-role-type="missing" sentence="51" predstart="23" predend="23" pos="VERB"/>
  <implicit role="arg2|release.01" recoverable="False" implicit-role-type="missing" sentence="52" predstart="6" predend="6" pos="NOUN"/>
  <implicit role="arg2|suggest.01" recoverable="False" implicit-role-type="missing" sentence="52" predstart="1" predend="1" pos="VERB"/>
  <implicit role="arg0|release.01" recoverable="False" implicit-role-type="missing" sentence="52" predstart="6" predend="6" pos="NOUN"/>
  <implicit role="arg2|use.01" recoverable="False" implicit-role-type="missing" sentence="52" predstart="18" predend="18" pos="VERB"/>
  <implicit role="arg0|use.01" recoverable="False" implicit-role-type="missing" sentence="52" predstart="18" predend="18" pos="VERB"/>
  <implicit role="arg0|discontinue.01" recoverable="False" implicit-role-type="missing" sentence="52" predstart="2" predend="2" pos="VERB"/>
  <implicit role="arg2|recommend.01" recoverable="False" implicit-role-type="missing" sentence="8" predstart="11" predend="11" pos="VERB"/>
  <implicit role="arg2|dole_out.01" recoverable="False" implicit-role-type="missing" sentence="8" predstart="14" predend="14" pos="VERB"/>
  <implicit role="arg0|recommend.01" recoverable="False" implicit-role-type="missing" sentence="8" predstart="11" predend="11" pos="VERB"/>
  <implicit role="arg4|recommend.01" recoverable="False" implicit-role-type="missing" sentence="8" predstart="11" predend="11" pos="VERB"/>
  <implicit role="arg2|know.01" recoverable="False" implicit-role-type="missing" sentence="8" predstart="4" predend="4" pos="VERB"/>
  <implicit role="arg3|take.01" recoverable="False" implicit-role-type="missing" sentence="1" predstart="4" predend="4" pos="VERB"/>
  <implicit role="arg2|suggest.01" recoverable="False" implicit-role-type="missing" sentence="1" predstart="12" predend="12" pos="VERB"/>
  <implicit role="arg2|take.01" recoverable="False" implicit-role-type="missing" sentence="1" predstart="4" predend="4" pos="VERB"/>
  <implicit role="arg0|dry.08" recoverable="False" implicit-role-type="missing" sentence="1" predstart="23" predend="23" pos="ADJ"/>
  <implicit role="arg1|swallow.01" recoverable="False" implicit-role-type="missing" sentence="1" predstart="31" predend="31" pos="ADJ"/>
  <implicit role="arg0|suggest.01" recoverable="False" implicit-role-type="missing" sentence="1" predstart="12" predend="12" pos="VERB"/>
  <implicit role="arg0|wake_up.02" recoverable="False" implicit-role-type="missing" sentence="1" predstart="20" predend="20" pos="VERB"/>
  <implicit role="arg2|wake_up.02" recoverable="False" implicit-role-type="missing" sentence="1" predstart="20" predend="20" pos="VERB"/>
  <implicit role="arg2|dry.08" recoverable="False" implicit-role-type="missing" sentence="1" predstart="23" predend="23" pos="ADJ"/>
  <implicit role="arg0|burn.01" recoverable="False" implicit-role-type="missing" sentence="2" predstart="8" predend="8" pos="VERB"/>
  <implicit role="arg0|crack.02" recoverable="False" implicit-role-type="missing" sentence="2" predstart="21" predend="21" pos="VERB"/>
  <implicit role="arg2|crack.02" recoverable="False" implicit-role-type="missing" sentence="2" predstart="21" predend="21" pos="VERB"/>
  <implicit role="arg0|dry.08" recoverable="False" implicit-role-type="missing" sentence="2" predstart="14" predend="14" pos="ADJ"/>
  <implicit role="arg1|develop.01" recoverable="False" implicit-role-type="missing" sentence="2" predstart="18" predend="18" pos="VERB"/>
  <implicit role="arg2|dry.08" recoverable="False" implicit-role-type="missing" sentence="2" predstart="14" predend="14" pos="ADJ"/>
  <implicit role="arg2|begin.01" recoverable="False" implicit-role-type="missing" sentence="2" predstart="16" predend="16" pos="VERB"/>
  <implicit role="arg1|crack.02" recoverable="False" implicit-role-type="missing" sentence="2" predstart="21" predend="21" pos="VERB"/>
  <implicit role="arg2|take.01" recoverable="False" implicit-role-type="missing" sentence="0" predstart="5" predend="5" pos="VERB"/>
  <implicit role="arg0|conceive.01" recoverable="False" implicit-role-type="missing" sentence="0" predstart="2" predend="2" pos="ADJ"/>
  <implicit role="arg2|case.04" recoverable="False" implicit-role-type="missing" sentence="0" predstart="27" predend="27" pos="NOUN"/>
  <implicit role="arg2|good.02" recoverable="False" implicit-role-type="missing" sentence="0" predstart="9" predend="9" pos="ADJ"/>
  <implicit role="arg3|take.01" recoverable="False" implicit-role-type="missing" sentence="0" predstart="5" predend="5" pos="VERB"/>
  <implicit role="arg2|get.01" recoverable="False" implicit-role-type="missing" sentence="6" predstart="13" predend="13" pos="VERB"/>
  <implicit role="arg1|reply.01" recoverable="False" implicit-role-type="missing" sentence="6" predstart="25" predend="25" pos="VERB"/>
  <implicit role="arg2|dry.02" recoverable="False" implicit-role-type="missing" sentence="6" predstart="7" predend="7" pos="ADJ"/>
  <implicit role="arg2|dry.08" recoverable="False" implicit-role-type="missing" sentence="6" predstart="7" predend="7" pos="ADJ"/>
  <implicit role="arg3|get.01" recoverable="False" implicit-role-type="missing" sentence="6" predstart="13" predend="13" pos="VERB"/>
  <implicit role="arg0|dry.08" recoverable="False" implicit-role-type="missing" sentence="6" predstart="7" predend="7" pos="ADJ"/>
  <implicit role="arg2|stop.01" recoverable="False" implicit-role-type="missing" sentence="3" predstart="1" predend="1" pos="VERB"/>
  <implicit role="arg4|go.01" recoverable="False" implicit-role-type="missing" sentence="3" predstart="8" predend="8" pos="VERB"/>
  <implicit role="arg2|go.01" recoverable="False" implicit-role-type="missing" sentence="3" predstart="8" predend="8" pos="VERB"/>
  <implicit role="arg3|go.01" recoverable="False" implicit-role-type="missing" sentence="3" predstart="8" predend="8" pos="VERB"/>
</ISRLSPANS>
