<?xml version="1.0" ?>
<!DOCTYPE ISRLSPANS SYSTEM "isrl.dtd">
<ISRLSPANS sourcefile="amrsamesent_713">

<implicit role="arg1|say.01" recoverable="True" implicit-role-type="same-sentence" predstart="2" predend="2" sentence="0">
    <candidate sentence="0" start="14" end="15"/>
</implicit>
<implicit role="arg1|post.01" recoverable="False" implicit-role-type="missing" predstart="19" predend="19" sentence="0"/>
<implicit role="arg2|read.01" recoverable="False" implicit-role-type="missing" predstart="9" predend="9" sentence="0"/>
<implicit role="arg0|request_confirmation.91" recoverable="False" implicit-role-type="missing" predstart="8" predend="8" sentence="0"/>
<implicit role="arg2|think.01" recoverable="False" implicit-role-type="missing" predstart="54" predend="54" sentence="0"/>
<implicit role="arg2|resemble.01" recoverable="False" implicit-role-type="missing" predstart="42" predend="42" sentence="0"/>
<implicit role="arg2|think.01" recoverable="False" implicit-role-type="missing" predstart="51" predend="51" sentence="0"/>
<implicit role="arg0|contrast.01" recoverable="False" implicit-role-type="missing" predstart="43" predend="43" sentence="0"/>
<implicit role="arg0|stuff.01" recoverable="False" implicit-role-type="missing" predstart="56" predend="56" sentence="0"/>
<implicit role="arg2|seem.01" recoverable="False" implicit-role-type="missing" predstart="41" predend="41" sentence="0"/>
</ISRLSPANS>

