<?xml version="1.0" ?>
<!DOCTYPE ISRLSPANS SYSTEM "isrl.dtd">
<ISRLSPANS sourcefile="amrsamesent_3785">

<implicit role="arg1|motivate.01" recoverable="True" implicit-role-type="same-sentence" predstart="15" predend="15" sentence="0">
    <candidate sentence="0" start="3" end="4"/>
</implicit>

<implicit role="arg0|make.02" recoverable="True" implicit-role-type="same-sentence" predstart="17" predend="17" sentence="0">
    <candidate sentence="0" start="3" end="4"/>
</implicit>
<implicit role="arg2|be_from.91" recoverable="False" implicit-role-type="missing" predstart="1" predend="1" sentence="0"/>
<implicit role="arg2|free.04" recoverable="False" implicit-role-type="missing" predstart="22" predend="22" sentence="0"/>
<implicit role="arg1|honor.01" recoverable="False" implicit-role-type="missing" predstart="8" predend="8" sentence="0"/>
<implicit role="arg0|secure.02" recoverable="False" implicit-role-type="missing" predstart="24" predend="24" sentence="0"/>
</ISRLSPANS>

