[{"sentence_id": "wsj_0443.0", "sentence": "0", "speaker": "n/a"}, {"sentence_id": "wsj_0443.1", "sentence": "1", "speaker": "n/a"}, {"sentence_id": "wsj_0443.2", "sentence": "2", "speaker": "n/a"}, {"sentence_id": "wsj_0443.3", "sentence": "3", "speaker": "n/a"}, {"sentence_id": "wsj_0443.4", "sentence": "4", "speaker": "n/a"}, {"sentence_id": "wsj_0443.5", "sentence": "5", "speaker": "n/a"}, {"sentence_id": "wsj_0443.6", "sentence": "6", "speaker": "n/a"}, {"sentence_id": "wsj_0443.7", "sentence": "7", "speaker": "n/a"}, {"sentence_id": "wsj_0443.8", "sentence": "8", "speaker": "n/a"}, {"sentence_id": "wsj_0443.9", "sentence": "9", "speaker": "n/a"}, {"sentence_id": "wsj_0443.10", "sentence": "10", "speaker": "n/a"}, {"sentence_id": "wsj_0443.11", "sentence": "11", "speaker": "n/a"}, {"sentence_id": "wsj_0443.12", "sentence": "12", "speaker": "n/a"}, {"sentence_id": "wsj_0443.13", "sentence": "13", "speaker": "n/a"}, {"sentence_id": "wsj_0443.14", "sentence": "14", "speaker": "n/a"}, {"sentence_id": "wsj_0443.15", "sentence": "15", "speaker": "n/a"}, {"sentence_id": "wsj_0443.16", "sentence": "16", "speaker": "n/a"}, {"sentence_id": "wsj_0443.17", "sentence": "17", "speaker": "n/a"}, {"sentence_id": "wsj_0443.18", "sentence": "18", "speaker": "n/a"}, {"sentence_id": "wsj_0443.19", "sentence": "19", "speaker": "n/a"}, {"sentence_id": "wsj_0443.20", "sentence": "20", "speaker": "n/a"}, {"sentence_id": "wsj_0443.21", "sentence": "21", "speaker": "n/a"}, {"sentence_id": "wsj_0443.22", "sentence": "22", "speaker": "n/a"}, {"sentence_id": "wsj_0443.23", "sentence": "23", "speaker": "n/a"}]