[{"sentence_id": "chtb_0177.0", "sentence": "0", "speaker": "n/a"}, {"sentence_id": "chtb_0177.1", "sentence": "1", "speaker": "n/a"}, {"sentence_id": "chtb_0177.2", "sentence": "2", "speaker": "n/a"}, {"sentence_id": "chtb_0177.3", "sentence": "3", "speaker": "n/a"}, {"sentence_id": "chtb_0177.4", "sentence": "4", "speaker": "n/a"}, {"sentence_id": "chtb_0177.5", "sentence": "5", "speaker": "n/a"}, {"sentence_id": "chtb_0177.6", "sentence": "6", "speaker": "n/a"}, {"sentence_id": "chtb_0177.7", "sentence": "7", "speaker": "n/a"}, {"sentence_id": "chtb_0177.8", "sentence": "8", "speaker": "n/a"}, {"sentence_id": "chtb_0177.9", "sentence": "9", "speaker": "n/a"}]