[{"sentence_id": "nbc_0025.0", "sentence": "0", "speaker": "n/a"}, {"sentence_id": "nbc_0025.1", "sentence": "1", "speaker": "n/a"}, {"sentence_id": "nbc_0025.2", "sentence": "2", "speaker": "n/a"}, {"sentence_id": "nbc_0025.3", "sentence": "3", "speaker": "n/a"}, {"sentence_id": "nbc_0025.4", "sentence": "4", "speaker": "n/a"}, {"sentence_id": "nbc_0025.5", "sentence": "5", "speaker": "n/a"}, {"sentence_id": "nbc_0025.6", "sentence": "6", "speaker": "n/a"}, {"sentence_id": "nbc_0025.7", "sentence": "7", "speaker": "n/a"}, {"sentence_id": "nbc_0025.8", "sentence": "8", "speaker": "n/a"}]